prediction/__init__.py
prediction/io/__init__.py
prediction/io/load_data.py
prediction/preprocess/__init__.py
prediction/preprocess/bikeformat.py
prediction/vis/__init__.py
bikechallenge_ng-0.0.1.dist-info/METADATA
bikechallenge_ng-0.0.1.dist-info/WHEEL
bikechallenge_ng-0.0.1.dist-info/top_level.txt
bikechallenge_ng-0.0.1.dist-info/RECORD
