Metadata-Version: 2.1
Name: bikechallenge-ng
Version: 0.0.1
Summary: Prediction the number of bikes crossing 
Home-page: https://github.com/goujilinouhaila-coder/Bike_Challenge.git
Author: Goujili Nouhaila
Author-email: goujilinouhaila@gmail.com
License: MIT
Platform: UNKNOWN
